conftest.py
dj_easy_log.py
test_easy_log.py
django_easy_logging-0.70.dist-info/WHEEL
django_easy_logging-0.70.dist-info/METADATA
django_easy_logging-0.70.dist-info/licenses/LICENSE
django_easy_logging-0.70.dist-info/RECORD
