Metadata-Version: 2.1
Name: django-easy-logging
Version: 0.70
Summary: Easy Django logging with Loguru
License: MIT
Author-email: Paul Bailey <paul@neutron.studio>
Requires-Python: >=3.7
Requires-Dist: loguru>=0.7.0
Project-URL: homepage, https://github.com/neutron-sync/django-easy-logging
